Workbook

Sheet Oyster
A1: OYSTER MUSHROOMS - PRODUCTION CALCULATOR
A3: PRODUCTION INPUTS
A4: Parameter | B4: Value | C4: Unit | D4: Notes
A5: Target weekly output | B5: 20 | C5: kg | D5: Your weekly sales target
A6: Substrate bag weight | B6: 5 | C6: kg | D6: Hydrated weight of prepared bag
A7: Dry substrate % | B7: 25 | C7: % | D7: Typical 25% for straw/sawdust
A8: Biological efficiency | B8: 100 | C8: % | D8: Oyster 100-150%, LM 75-100%
A9: Incubation period | B9: 2.5 | C9: weeks | D9: Time in incubation
A10: Fruiting period | B10: 2.5 | C10: weeks | D10: Time for 2 flushes
A12: COST INPUTS (AUD)
A13: Cost Item | B13: Amount | C13: Unit | D13: Notes
A14: Substrate per bag | B14: 2.5 | C14: $/bag | D14: Straw, sawdust, supplements
A15: Spawn per bag | B15: 1.5 | C15: $/bag | D15: Grain spawn allocation
A16: Bag & filter | B16: 0.8 | C16: $/bag | D16: Autoclavable grow bag
A17: Labor per bag | B17: 1 | C17: $/bag | D17: Your time value
A18: Utilities per bag | B18: 0.5 | C18: $/bag | D18: Power, water, cooling
A19: TOTAL COST PER BAG | B19: =SUM(B14:B18) -> 6.3 | C19: $/bag | D19: =SUM of all costs above -> #NAME?
A21: REVENUE
A22: Sale price per kg | B22: 25 | C22: $/kg | D22: Farm gate price
A24: CALCULATED PRODUCTION
A25: Dry substrate per bag | B25: =B6*B7/100 -> 1.25 | C25: kg
A26: Yield per bag | B26: =B25*B8/100 -> 1.25 | C26: kg | D26: Fresh mushrooms from 2 flushes
A27: Total cycle length | B27: =B9+B10 -> 5 | C27: weeks
A28: Bags to prep per week | B28: =CEILING(B5/B26,1) -> 16 | C28: bags | D28: Bags to pasteurize weekly
A29: Total bags in rotation | B29: =B28*B27 -> 80 | C29: bags | D29: All bags in system at once
A31: FINANCIAL RESULTS
A32: Metric | B32: Weekly | C32: Monthly | D32: Yearly
A33: Gross Revenue | B33: =B5*B22 -> 500 | C33: =B33*4.33 -> 2165 | D33: =B33*52 -> 26000
A34: Total Costs | B34: =B28*B19 -> 100.8 | C34: =B34*4.33 -> 436.464 | D34: =B34*52 -> 5241.6
A35: GROSS PROFIT | B35: =B33-B34 -> 399.2 | C35: =C33-C34 -> 1728.536 | D35: =D33-D34 -> 20758.4
A36: Profit Margin | B36: =B35/B33 -> 0.7984
A38: KEY METRICS
A39: Cost per kg produced | B39: =B19/B26 -> 5.04 | C39: $/kg | D39: Your breakeven price
A40: Profit per kg | B40: =B22-(B19/B26) -> 19.96 | C40: $/kg
A41: Profit per bag | B41: =(B22*B26)-B19 -> 24.95 | C41: $/bag

Sheet Lions Mane
A1: LION'S MANE - PRODUCTION CALCULATOR
A3: PRODUCTION INPUTS
A4: Parameter | B4: Value | C4: Unit | D4: Notes
A5: Target weekly output | B5: 10 | C5: kg | D5: Your weekly sales target
A6: Substrate bag weight | B6: 5 | C6: kg | D6: Hydrated weight of prepared bag
A7: Dry substrate % | B7: 25 | C7: % | D7: Typical 25% for straw/sawdust
A8: Biological efficiency | B8: 80 | C8: % | D8: Oyster 100-150%, LM 75-100%
A9: Incubation period | B9: 3.5 | C9: weeks | D9: Time in incubation
A10: Fruiting period | B10: 3.5 | C10: weeks | D10: Time for 2 flushes
A12: COST INPUTS (AUD)
A13: Cost Item | B13: Amount | C13: Unit | D13: Notes
A14: Substrate per bag | B14: 3 | C14: $/bag | D14: Straw, sawdust, supplements
A15: Spawn per bag | B15: 2 | C15: $/bag | D15: Grain spawn allocation
A16: Bag & filter | B16: 0.8 | C16: $/bag | D16: Autoclavable grow bag
A17: Labor per bag | B17: 1.5 | C17: $/bag | D17: Your time value
A18: Utilities per bag | B18: 1 | C18: $/bag | D18: Power, water, cooling
A19: TOTAL COST PER BAG | B19: =SUM(B14:B18) -> 8.3 | C19: $/bag | D19: =SUM of all costs above -> #NAME?
A21: REVENUE
A22: Sale price per kg | B22: 35 | C22: $/kg | D22: Farm gate price
A24: CALCULATED PRODUCTION
A25: Dry substrate per bag | B25: =B6*B7/100 -> 1.25 | C25: kg
A26: Yield per bag | B26: =B25*B8/100 -> 1 | C26: kg | D26: Fresh mushrooms from 2 flushes
A27: Total cycle length | B27: =B9+B10 -> 7 | C27: weeks
A28: Bags to prep per week | B28: =CEILING(B5/B26,1) -> 10 | C28: bags | D28: Bags to pasteurize weekly
A29: Total bags in rotation | B29: =B28*B27 -> 70 | C29: bags | D29: All bags in system at once
A31: FINANCIAL RESULTS
A32: Metric | B32: Weekly | C32: Monthly | D32: Yearly
A33: Gross Revenue | B33: =B5*B22 -> 350 | C33: =B33*4.33 -> 1515.5 | D33: =B33*52 -> 18200
A34: Total Costs | B34: =B28*B19 -> 83 | C34: =B34*4.33 -> 359.39 | D34: =B34*52 -> 4316
A35: GROSS PROFIT | B35: =B33-B34 -> 267 | C35: =C33-C34 -> 1156.11 | D35: =D33-D34 -> 13884
A36: Profit Margin | B36: =B35/B33 -> 0.76285714
A38: KEY METRICS
A39: Cost per kg produced | B39: =B19/B26 -> 8.3 | C39: $/kg | D39: Your breakeven price
A40: Profit per kg | B40: =B22-(B19/B26) -> 26.7 | C40: $/kg
A41: Profit per bag | B41: =(B22*B26)-B19 -> 26.7 | C41: $/bag

Sheet Summary
A1: COMBINED OPERATION SUMMARY
A3: Metric | B3: Oyster | C3: Lion's Mane | D3: TOTAL
A4: Target kg/week | B4: =Oyster!B5 -> 20 | C4: ='Lions Mane'!B5 -> 10 | D4: =B4+C4 -> 30
A5: Yield per bag (kg) | B5: =Oyster!B26 -> 1.25 | C5: ='Lions Mane'!B26 -> 1
A6: Bags per week | B6: =Oyster!B28 -> 16 | C6: ='Lions Mane'!B28 -> 10 | D6: =B6+C6 -> 26
A7: Bags in rotation | B7: =Oyster!B29 -> 80 | C7: ='Lions Mane'!B29 -> 70 | D7: =B7+C7 -> 150
A8: Cost per bag | B8: =Oyster!B19 -> 6.3 | C8: ='Lions Mane'!B19 -> 8.3
A9: Sale price/kg | B9: =Oyster!B22 -> 25 | C9: ='Lions Mane'!B22 -> 35
A11: FINANCIAL SUMMARY
A12: Metric | B12: Oyster | C12: Lion's Mane | D12: TOTAL
A13: Weekly Revenue | B13: =Oyster!B33 -> 500 | C13: ='Lions Mane'!B33 -> 350 | D13: =B13+C13 -> 850
A14: Weekly Costs | B14: =Oyster!B34 -> 100.8 | C14: ='Lions Mane'!B34 -> 83 | D14: =B14+C14 -> 183.8
A15: Weekly Profit | B15: =Oyster!B35 -> 399.2 | C15: ='Lions Mane'!B35 -> 267 | D15: =B15+C15 -> 666.2
A16: Monthly Profit | B16: =Oyster!C35 -> 1728.536 | C16: ='Lions Mane'!C35 -> 1156.11 | D16: =B16+C16 -> 2884.646
A17: Yearly Profit | B17: =Oyster!D35 -> 20758.4 | C17: ='Lions Mane'!D35 -> 13884 | D17: =B17+C17 -> 34642.4
A20: SPACE CHECK - FRUITING ROOM
A21: Room size (sqm) | B21: 9
A22: Bags per sqm (4-tier) | B22: 12
A23: Max room capacity | B23: =B21*B22 -> 108 | C23: bags
A24: Bags in fruiting | B24: =(Oyster!B29 * Oyster!B10 / Oyster!B27) + ('Lions Mane'!B29 * 'Lions Mane'!B10 / 'Lions Mane'!B27) -> 75 | C24: bags
A25: Space utilization | B25: =B24/B23 -> 0.69444444
A26: Status | B26: =IF(B24<=B23,"OK - FITS","WARNING - OVER CAPACITY") -> OK - FITS

Sheet Scenario Planner
A1: SCENARIO PLANNER - What if I produce X kg/week?
A3: Oyster - vary target output
A4: Target kg/wk | B4: Bags/wk | C4: In Rotation | D4: Weekly Profit | E4: Monthly Profit | F4: Yearly Profit
A5: 5 | B5: =CEILING(A5/Oyster!B26,1) -> 4 | C5: =B5*Oyster!B27 -> 20 | D5: =(A5*Oyster!B22)-(B5*Oyster!B19) -> 99.8 | E5: =D5*4.33 -> 432.134 | F5: =D5*52 -> 5189.6
A6: 10 | B6: =CEILING(A6/Oyster!B26,1) -> 8 | C6: =B6*Oyster!B27 -> 40 | D6: =(A6*Oyster!B22)-(B6*Oyster!B19) -> 199.6 | E6: =D6*4.33 -> 864.268 | F6: =D6*52 -> 10379.2
A7: 15 | B7: =CEILING(A7/Oyster!B26,1) -> 12 | C7: =B7*Oyster!B27 -> 60 | D7: =(A7*Oyster!B22)-(B7*Oyster!B19) -> 299.4 | E7: =D7*4.33 -> 1296.402 | F7: =D7*52 -> 15568.8
A8: 20 | B8: =CEILING(A8/Oyster!B26,1) -> 16 | C8: =B8*Oyster!B27 -> 80 | D8: =(A8*Oyster!B22)-(B8*Oyster!B19) -> 399.2 | E8: =D8*4.33 -> 1728.536 | F8: =D8*52 -> 20758.4
A9: 25 | B9: =CEILING(A9/Oyster!B26,1) -> 20 | C9: =B9*Oyster!B27 -> 100 | D9: =(A9*Oyster!B22)-(B9*Oyster!B19) -> 499 | E9: =D9*4.33 -> 2160.67 | F9: =D9*52 -> 25948
A10: 30 | B10: =CEILING(A10/Oyster!B26,1) -> 24 | C10: =B10*Oyster!B27 -> 120 | D10: =(A10*Oyster!B22)-(B10*Oyster!B19) -> 598.8 | E10: =D10*4.33 -> 2592.804 | F10: =D10*52 -> 31137.6
A11: 40 | B11: =CEILING(A11/Oyster!B26,1) -> 32 | C11: =B11*Oyster!B27 -> 160 | D11: =(A11*Oyster!B22)-(B11*Oyster!B19) -> 798.4 | E11: =D11*4.33 -> 3457.072 | F11: =D11*52 -> 41516.8
A12: 50 | B12: =CEILING(A12/Oyster!B26,1) -> 40 | C12: =B12*Oyster!B27 -> 200 | D12: =(A12*Oyster!B22)-(B12*Oyster!B19) -> 998 | E12: =D12*4.33 -> 4321.34 | F12: =D12*52 -> 51896
A15: Lion's Mane - vary target output
A16: Target kg/wk | B16: Bags/wk | C16: In Rotation | D16: Weekly Profit | E16: Monthly Profit | F16: Yearly Profit
A17: 3 | B17: =CEILING(A17/'Lions Mane'!B26,1) -> 3 | C17: =B17*'Lions Mane'!B27 -> 21 | D17: =(A17*'Lions Mane'!B22)-(B17*'Lions Mane'!B19) -> 80.1 | E17: =D17*4.33 -> 346.833 | F17: =D17*52 -> 4165.2
A18: 5 | B18: =CEILING(A18/'Lions Mane'!B26,1) -> 5 | C18: =B18*'Lions Mane'!B27 -> 35 | D18: =(A18*'Lions Mane'!B22)-(B18*'Lions Mane'!B19) -> 133.5 | E18: =D18*4.33 -> 578.055 | F18: =D18*52 -> 6942
A19: 8 | B19: =CEILING(A19/'Lions Mane'!B26,1) -> 8 | C19: =B19*'Lions Mane'!B27 -> 56 | D19: =(A19*'Lions Mane'!B22)-(B19*'Lions Mane'!B19) -> 213.6 | E19: =D19*4.33 -> 924.888 | F19: =D19*52 -> 11107.2
A20: 10 | B20: =CEILING(A20/'Lions Mane'!B26,1) -> 10 | C20: =B20*'Lions Mane'!B27 -> 70 | D20: =(A20*'Lions Mane'!B22)-(B20*'Lions Mane'!B19) -> 267 | E20: =D20*4.33 -> 1156.11 | F20: =D20*52 -> 13884
A21: 12 | B21: =CEILING(A21/'Lions Mane'!B26,1) -> 12 | C21: =B21*'Lions Mane'!B27 -> 84 | D21: =(A21*'Lions Mane'!B22)-(B21*'Lions Mane'!B19) -> 320.4 | E21: =D21*4.33 -> 1387.332 | F21: =D21*52 -> 16660.8
A22: 15 | B22: =CEILING(A22/'Lions Mane'!B26,1) -> 15 | C22: =B22*'Lions Mane'!B27 -> 105 | D22: =(A22*'Lions Mane'!B22)-(B22*'Lions Mane'!B19) -> 400.5 | E22: =D22*4.33 -> 1734.165 | F22: =D22*52 -> 20826
A23: 20 | B23: =CEILING(A23/'Lions Mane'!B26,1) -> 20 | C23: =B23*'Lions Mane'!B27 -> 140 | D23: =(A23*'Lions Mane'!B22)-(B23*'Lions Mane'!B19) -> 534 | E23: =D23*4.33 -> 2312.22 | F23: =D23*52 -> 27768
